{"document_id":"320001075733","content":"Container: OOCU8049862 | Consignee: AMER SPORTS EUROPEAN CENTER ELSA DC | Current shipment status: EMPTY_RETURNED\n\nParties & service: Consignee: AMER SPORTS EUROPEAN CENTER ELSA DC | Supplier\/Vendor: EAST WIND FOOTWEAR COMPANY LIMITED(0017207) | Manufacturer: EAST WIND FOOTWEAR COMPANY LIMITED(0017207) | Job type: OCB | Destination service: CY | Transport mode: SEA | Hot container flag: True | Booking approval status: (IN2021383)\n\nRouting & movements: Origin: KATTUPALLI(INKAT) | Load Port: KATTUPALLI(INKAT) | Transshipment Port: SOUTHAMPTON(GBSOU) | Discharge Port: LE HAVRE, FRANCE(FRLEH) | Place of Delivery: LE HAVRE, FRANCE(FRLEH) | Final Destination: SAINT VULBAS(FRSVB) || Route summary: Origin: KATTUPALLI(INKAT) -> Transshipment Port: SOUTHAMPTON(GBSOU) -> Discharge Port: LE HAVRE, FRANCE(FRLEH) -> Final: SAINT VULBAS(FRSVB) || Vessel summary: First vessel: HYUNDAI SINGAPORE | Final vessel: CMA CGM MANTA RAY || Carrier summary: Operated by CORPORATE SERVICE GMBH (COSCO CONTAINER LINE AGENCIES LTD)\n\nReferences: PO Numbers: 5302825068, 5302825068, 5302830553, 5302830557, 5302830567, 5302830572 | Booking Numbers: IN2021383, IN2021383 | FCR Numbers: IN2021383, IN2021712 | Ocean BL Numbers: MOLWMAA2400083, MOLWMAA2400083 | Service contract number: (IN2021383)\n\nStatus & timeline: DP delay status: on_time, Δ≈0 day(s). | FD delay status: delay, Δ≈6 day(s). || Milestones: Overall shipment status: EMPTY_RETURNED || Leg 1 (POR → Load Port) [COMPLETED]: KATTUPALLI(INKAT) → KATTUPALLI(INKAT); departed KATTUPALLI(INKAT) on 2025-01-03 (origin leg closed). || Leg 2 (Load Port → TS) [COMPLETED]: KATTUPALLI(INKAT) → SOUTHAMPTON(GBSOU); departed TS on 2025-04-02 || Leg 3 (TS → Discharge Port) [COMPLETED]: SOUTHAMPTON(GBSOU) → LE HAVRE, FRANCE(FRLEH); ocean leg into LE HAVRE, FRANCE(FRLEH) completed on 2025-04-03 (arrived on time vs ETA DP.) || Leg 4 (DP → Last CY) [COMPLETED]: LE HAVRE, FRANCE(FRLEH) → LE HAVRE, FRANCE(FRLEH); departed DP area on 2025-04-07, arrived last CY LE HAVRE, FRANCE(FRLEH) on 2025-04-03. || Leg 5 (Last CY → Final) [COMPLETED]: LE HAVRE, FRANCE(FRLEH) → SAINT VULBAS(FRSVB); empty container returned on 2025-04-22 (delayed by ~6 day(s) vs ETA FD.) || Critical dates: Stage 1 (POR → Load Port): KATTUPALLI(INKAT) → KATTUPALLI(INKAT) (ETD=2025-01-03, ATD=2025-01-03; departed on planned ETD) || Stage 2 (Load Port → TS): KATTUPALLI(INKAT) → SOUTHAMPTON(GBSOU) (departure 2025-04-02, arrival not recorded) || Stage 3 (TS → Discharge Port): SOUTHAMPTON(GBSOU) → LE HAVRE, FRANCE(FRLEH) (ETA DP=2025-04-03, ATA DP=2025-04-03, on time) || Stage 4 (DP → Last CY): LE HAVRE, FRANCE(FRLEH) → LE HAVRE, FRANCE(FRLEH) (departed DP area on 2025-04-07, arrived last CY at LE HAVRE, FRANCE(FRLEH) on 2025-04-03) || Stage 5 (Last CY → Final): LE HAVRE, FRANCE(FRLEH) → SAINT VULBAS(FRSVB) (ETA FD=2025-04-16, Delivery=N\/A, Empty return=2025-04-22, delayed by 6d) || Delay analysis: Final delivery leg (post-DP) is delayed versus ETA at final destination by ~6 day(s).; Last-mile from last CY to final destination \/ empty return took ~19 day(s), indicating inland \/ delivery-side delay. || Workflow\/data gaps: missing_delivery_event_with_empty_return\n\nCargo & CO2: Cargo metrics: weight 5748.38 kg volume 60.63 m3 | Cargo count: 558 CTN | Detail cargo: 5705 PR | CO2 emission: tank-on-wheel 1564.952 well-to-wheel 1704.1","metadata":{"job_no":"IN2SSA1437","container_number":"OOCU8049862","container_type":"C4","destination_service":"CY","consignee_raw":"AMER SPORTS EUROPEAN CENTER ELSA DC(0025833)","po_numbers":"5302825068, 5302825068, 5302830553, 5302830557, 5302830567, 5302830572","booking_numbers":"IN2021383, IN2021383","fcr_numbers":"IN2021383, IN2021712","obl_nos":"MOLWMAA2400083, MOLWMAA2400083","load_port":"KATTUPALLI(INKAT)","final_load_port":"SOUTHAMPTON(GBSOU)","discharge_port":"LE HAVRE, FRANCE(FRLEH)","last_cy_location":"LE HAVRE, FRANCE(FRLEH)","place_of_receipt":"KATTUPALLI(INKAT)","place_of_delivery":"LE HAVRE, FRANCE(FRLEH)","final_destination":"SAINT VULBAS(FRSVB)","first_vessel_name":"HYUNDAI SINGAPORE","final_carrier_name":"CORPORATE SERVICE GMBH","final_vessel_name":"CMA CGM MANTA RAY","true_carrier_scac_name":"COSCO CONTAINER LINE AGENCIES LTD","etd_lp_date":"2025-01-03","etd_flp_date":"2025-04-02","eta_dp_date":"2025-04-03","atd_lp_date":"2025-01-03","ata_flp_date":null,"atd_flp_date":"2025-04-02","derived_ata_dp_date":"2025-04-03","cargo_receiveds_date":"2024-12-25,2024-12-25","detention_free_days":null,"demurrage_free_days":null,"hot_container_flag":true,"supplier_vendor_name":"EAST WIND FOOTWEAR COMPANY LIMITED(0017207)","manufacturer_name":"EAST WIND FOOTWEAR COMPANY LIMITED(0017207)","ship_to_party_name":null,"booking_approval_status":"(IN2021383)","service_contract_number":"(IN2021383)","carrier_vehicle_load_date":"2025-01-02","carrier_vehicle_load_lcn":"KATTUPALLI PORT(PLEASE USE INKAT)(INKTP)","vehicle_departure_date":"2025-01-03","vehicle_departure_lcn":"KATTUPALLI PORT(PLEASE USE INKAT)(INKTP)","vehicle_arrival_date":"2025-04-03","vehicle_arrival_lcn":"LE HAVRE, FRANCE(FRLEH)","carrier_vehicle_unload_date":"2025-04-03","carrier_vehicle_unload_lcn":"LE HAVRE, FRANCE(FRLEH)","out_gate_from_dp_date":"2025-04-07","out_gate_from_dp_lcn":"LE HAVRE, FRANCE(FRLEH)","equipment_arrived_at_last_cy_date":"2025-04-03","equipment_arrived_at_last_cy_lcn":"LE HAVRE, FRANCE(FRLEH)","out_gate_at_last_cy_date":"2025-04-07","out_gate_at_last_cy_lcn":"LE HAVRE, FRANCE(FRLEH)","delivery_to_consignee_date":null,"delivery_to_consignee_lcn":null,"empty_container_return_date":"2025-04-22","empty_container_return_lcn":"LE HAVRE, FRANCE(FRLEH)","co2_tank_on_wheel":"1564.952","co2_well_to_wheel":"1704.1","job_type":"OCB","mcs_hbl":null,"transport_mode":"SEA","rail_load_dp_date":null,"rail_load_dp_lcn":null,"rail_departure_dp_date":null,"rail_departure_dp_lcn":null,"rail_arrival_destination_date":null,"rail_arrival_destination_lcn":null,"cargo_weight_kg":"5748.38","cargo_measure_cubic_meter":"60.63","cargo_count":"558","cargo_um":"CTN","cargo_detail_count":"5705","detail_cargo_um":"PR","consignee_name":"AMER SPORTS EUROPEAN CENTER ELSA DC","consignee_codes":["0025833"],"optimal_ata_dp_date":"2025-04-03","optimal_eta_fd_date":"2025-04-16","shipment_status":"EMPTY_RETURNED","vessel_summary":"First vessel: HYUNDAI SINGAPORE | Final vessel: CMA CGM MANTA RAY","carrier_summary":"Operated by CORPORATE SERVICE GMBH (COSCO CONTAINER LINE AGENCIES LTD)","port_route_summary":"Origin: KATTUPALLI(INKAT) -> Transshipment Port: SOUTHAMPTON(GBSOU) -> Discharge Port: LE HAVRE, FRANCE(FRLEH) -> Final: SAINT VULBAS(FRSVB)","delayed_dp":"on_time","dp_delayed_dur":0.0,"delayed_fd":"delay","fd_delayed_dur":6.0,"critical_dates_summary":"Stage 1 (POR → Load Port): KATTUPALLI(INKAT) → KATTUPALLI(INKAT) (ETD=2025-01-03, ATD=2025-01-03; departed on planned ETD) || Stage 2 (Load Port → TS): KATTUPALLI(INKAT) → SOUTHAMPTON(GBSOU) (departure 2025-04-02, arrival not recorded) || Stage 3 (TS → Discharge Port): SOUTHAMPTON(GBSOU) → LE HAVRE, FRANCE(FRLEH) (ETA DP=2025-04-03, ATA DP=2025-04-03, on time) || Stage 4 (DP → Last CY): LE HAVRE, FRANCE(FRLEH) → LE HAVRE, FRANCE(FRLEH) (departed DP area on 2025-04-07, arrived last CY at LE HAVRE, FRANCE(FRLEH) on 2025-04-03) || Stage 5 (Last CY → Final): LE HAVRE, FRANCE(FRLEH) → SAINT VULBAS(FRSVB) (ETA FD=2025-04-16, Delivery=N\/A, Empty return=2025-04-22, delayed by 6d)","delay_reason_summary":"Final delivery leg (post-DP) is delayed versus ETA at final destination by ~6 day(s).; Last-mile from last CY to final destination \/ empty return took ~19 day(s), indicating inland \/ delivery-side delay.","workflow_gap_flags":"missing_delivery_event_with_empty_return","milestones":"Overall shipment status: EMPTY_RETURNED || Leg 1 (POR → Load Port) [COMPLETED]: KATTUPALLI(INKAT) → KATTUPALLI(INKAT); departed KATTUPALLI(INKAT) on 2025-01-03 (origin leg closed). || Leg 2 (Load Port → TS) [COMPLETED]: KATTUPALLI(INKAT) → SOUTHAMPTON(GBSOU); departed TS on 2025-04-02 || Leg 3 (TS → Discharge Port) [COMPLETED]: SOUTHAMPTON(GBSOU) → LE HAVRE, FRANCE(FRLEH); ocean leg into LE HAVRE, FRANCE(FRLEH) completed on 2025-04-03 (arrived on time vs ETA DP.) || Leg 4 (DP → Last CY) [COMPLETED]: LE HAVRE, FRANCE(FRLEH) → LE HAVRE, FRANCE(FRLEH); departed DP area on 2025-04-07, arrived last CY LE HAVRE, FRANCE(FRLEH) on 2025-04-03. || Leg 5 (Last CY → Final) [COMPLETED]: LE HAVRE, FRANCE(FRLEH) → SAINT VULBAS(FRSVB); empty container returned on 2025-04-22 (delayed by ~6 day(s) vs ETA FD.)","source_month_tag":"jan25","source_group":"shipment_jan25"},"consignee_code":"['0025833']"}
